{"ts":1772979878949,"version":2,"gameState":{"xp":2857,"level":10,"totalStars":219,"streak":7,"lastPlayDate":"Sun Mar 08 2026","streakShield":true,"gamesPlayed":{"bubble":29,"memory":2,"lightning":22,"scramble":0,"falling":0,"bingo":2,"truefalse":18,"sprint":2,"wordspy":4,"matchup":14},"achievements":["first_steps","combo_master","speed_demon","word_wizard","week_warrior","vocab_hero"],"dailyChallenge":{"date":"Sun Mar 08 2026","type":"play2","progress":2,"completed":true},"bonusChallenge":{"date":"Sun Mar 08 2026","type":"stars3x2","progress":2,"completed":true,"tier":1,"xpTarget":2860,"xpEarned":775},"dailyTimeGoal":{"date":"Sun Mar 08 2026","targetMin":25,"playedSec":336,"completed":false},"todayGamesPlayed":{"date":"Sun Mar 08 2026","modes":["truefalse","matchup","lightning"],"rounds":3,"maxCombo":4,"maxStreak":6,"gotStars3":true,"masteredNewWord":true},"fallingHighScore":0,"sprintHighScore":14,"testHistory":[{"date":1772717032453,"totalWords":40,"correct":38,"wrong":2,"grade":"A","pct":95,"wrongWords":[{"english":"desert","hebrew":"מדבר"},{"english":"cousin","hebrew":"בן דוד / בת דודה"}]}],"firstTime":false,"milestonesShown":["milestone10","milestone25","st10_Thu Mar 05 2026","st30_Thu Mar 05 2026","st10_Sat Mar 07 2026","milestone50"],"screenTimeBank":{"earned":14,"redeemed":9,"todayEarned":7.5,"todayDate":"Sun Mar 08 2026"}},"history":[{"ts":1772467499683,"game":"lightning","correct":7,"total":10,"stars":2,"xp":70,"accuracy":70},{"ts":1772467714352,"game":"bingo","correct":0,"total":0,"stars":3,"xp":16,"accuracy":0},{"ts":1772467898656,"game":"truefalse","correct":14,"total":15,"stars":3,"xp":240,"accuracy":93},{"ts":1772468001118,"game":"lightning","correct":8,"total":10,"stars":2,"xp":80,"accuracy":80},{"ts":1772468188780,"game":"sprint","correct":0,"total":0,"stars":3,"xp":19,"accuracy":0},{"ts":1772468341766,"game":"truefalse","correct":14,"total":15,"stars":3,"xp":240,"accuracy":93},{"ts":1772468393988,"game":"wordspy","correct":0,"total":0,"stars":3,"xp":8,"accuracy":0},{"ts":1772555070708,"game":"truefalse","correct":10,"total":15,"stars":1,"xp":148,"accuracy":67},{"ts":1772555216792,"game":"lightning","correct":7,"total":10,"stars":2,"xp":70,"accuracy":70},{"ts":1772555443016,"game":"truefalse","correct":11,"total":15,"stars":2,"xp":166,"accuracy":73},{"ts":1772555744659,"game":"lightning","correct":9,"total":10,"stars":3,"xp":90,"accuracy":90},{"ts":1772555873438,"game":"matchup","correct":15,"total":15,"stars":3,"xp":320,"accuracy":100},{"ts":1772556070445,"game":"sprint","correct":0,"total":0,"stars":3,"xp":19,"accuracy":0},{"ts":1772560498247,"game":"wordspy","correct":0,"total":0,"stars":3,"xp":8,"accuracy":0},{"ts":1772561230123,"game":"lightning","correct":8,"total":10,"stars":2,"xp":80,"accuracy":80},{"ts":1772561514827,"game":"lightning","correct":10,"total":10,"stars":3,"xp":120,"accuracy":100},{"ts":1772614804784,"game":"truefalse","correct":12,"total":15,"stars":2,"xp":182,"accuracy":80},{"ts":1772622108855,"game":"lightning","correct":10,"total":10,"stars":3,"xp":120,"accuracy":100,"duration":70},{"ts":1772622253355,"game":"truefalse","correct":14,"total":15,"stars":3,"xp":240,"accuracy":93,"duration":68},{"ts":1772622369791,"game":"bubble","correct":9,"total":10,"stars":3,"xp":330,"accuracy":90,"duration":93},{"ts":1772626813797,"game":"wordspy","correct":8,"total":8,"stars":3,"xp":89,"accuracy":100,"duration":120},{"ts":1772626923052,"game":"bubble","correct":7,"total":10,"stars":2,"xp":320,"accuracy":70,"duration":79},{"ts":1772634804836,"game":"lightning","correct":7,"total":10,"stars":2,"xp":70,"accuracy":70,"duration":69},{"ts":1772634865401,"game":"truefalse","correct":15,"total":15,"stars":3,"xp":67,"accuracy":100,"duration":16},{"ts":1772634892048,"game":"bubble","correct":2,"total":3,"stars":1,"xp":40,"accuracy":67,"duration":20},{"ts":1772634909388,"game":"bubble","correct":3,"total":3,"stars":1,"xp":80,"accuracy":100,"duration":38},{"ts":1772639614863,"game":"lightning","correct":7,"total":10,"stars":2,"xp":87,"accuracy":70,"duration":54},{"ts":1772639798442,"game":"lightning","correct":7,"total":10,"stars":2,"xp":70,"accuracy":70,"duration":97},{"ts":1772640019328,"game":"bubble","correct":7,"total":10,"stars":2,"xp":250,"accuracy":70,"duration":116},{"ts":1772640246192,"game":"matchup","correct":15,"total":15,"stars":2,"xp":300,"accuracy":100,"duration":81},{"ts":1772640317295,"game":"memory","correct":6,"total":6,"stars":1,"xp":60,"accuracy":100,"duration":60},{"ts":1772640402341,"game":"bubble","correct":10,"total":10,"stars":3,"xp":420,"accuracy":100,"duration":64},{"ts":1772640488763,"game":"bubble","correct":7,"total":10,"stars":2,"xp":200,"accuracy":70,"duration":150},{"ts":1772640544645,"game":"bubble","correct":10,"total":10,"stars":3,"xp":420,"accuracy":100,"duration":206},{"ts":1772643917071,"game":"matchup","correct":15,"total":15,"stars":2,"xp":300,"accuracy":100,"duration":98},{"ts":1772643993389,"game":"matchup","correct":15,"total":15,"stars":3,"xp":320,"accuracy":100,"duration":175},{"ts":1772644132246,"game":"matchup","correct":15,"total":15,"stars":3,"xp":320,"accuracy":100,"duration":58},{"ts":1772644212383,"game":"matchup","correct":15,"total":15,"stars":3,"xp":320,"accuracy":100,"duration":138},{"ts":1772644262180,"game":"matchup","correct":15,"total":15,"stars":3,"xp":279,"accuracy":100,"duration":187},{"ts":1772644320231,"game":"matchup","correct":15,"total":15,"stars":2,"xp":250,"accuracy":100,"duration":246},{"ts":1772654265055,"game":"truefalse","correct":13,"total":15,"stars":2,"xp":212,"accuracy":87,"duration":58},{"ts":1772654332935,"game":"bubble","correct":7,"total":10,"stars":2,"xp":260,"accuracy":70,"duration":59},{"ts":1772654400398,"game":"bubble","correct":8,"total":10,"stars":3,"xp":240,"accuracy":80,"duration":127},{"ts":1772654471973,"game":"bubble","correct":8,"total":10,"stars":3,"xp":260,"accuracy":80,"duration":198},{"ts":1772654525185,"game":"bubble","correct":10,"total":10,"stars":3,"xp":420,"accuracy":100,"duration":251},{"ts":1772654591008,"game":"bubble","correct":9,"total":10,"stars":3,"xp":330,"accuracy":90,"duration":317},{"ts":1772654791136,"game":"matchup","correct":15,"total":15,"stars":3,"xp":320,"accuracy":100,"duration":61},{"ts":1772654828740,"game":"matchup","correct":15,"total":15,"stars":3,"xp":286,"accuracy":100,"duration":98},{"ts":1772654869679,"game":"matchup","correct":15,"total":15,"stars":3,"xp":257,"accuracy":100,"duration":139},{"ts":1772711909645,"game":"matchup","correct":15,"total":15,"stars":2,"xp":300,"accuracy":100,"duration":51},{"ts":1772711955579,"game":"matchup","correct":15,"total":15,"stars":2,"xp":300,"accuracy":100,"duration":97},{"ts":1772716286486,"game":"truefalse","correct":14,"total":15,"stars":3,"xp":246,"accuracy":93,"duration":94},{"ts":1772716297510,"game":"truefalse","correct":14,"total":15,"stars":3,"xp":0,"accuracy":93,"duration":105},{"ts":1772716303624,"game":"truefalse","correct":15,"total":15,"stars":3,"xp":37,"accuracy":100,"duration":111},{"ts":1772716465302,"game":"truefalse","correct":14,"total":15,"stars":3,"xp":246,"accuracy":93,"duration":273},{"ts":1772716471046,"game":"truefalse","correct":15,"total":15,"stars":3,"xp":37,"accuracy":100,"duration":278},{"ts":1772716559204,"game":"truefalse","correct":13,"total":15,"stars":2,"xp":218,"accuracy":87,"duration":367},{"ts":1772716566972,"game":"truefalse","correct":15,"total":15,"stars":3,"xp":51,"accuracy":100,"duration":374},{"ts":1772716678399,"game":"bubble","correct":8,"total":10,"stars":3,"xp":240,"accuracy":80,"duration":99},{"ts":1772716691303,"game":"bubble","correct":2,"total":2,"stars":1,"xp":50,"accuracy":100,"duration":112},{"ts":1772716749147,"game":"bubble","correct":9,"total":10,"stars":3,"xp":300,"accuracy":90,"duration":170},{"ts":1772716810650,"game":"bubble","correct":10,"total":10,"stars":3,"xp":420,"accuracy":100,"duration":231},{"ts":1772727217662,"game":"bingo","correct":16,"total":16,"stars":3,"xp":100,"accuracy":100,"duration":129},{"ts":1772727362046,"game":"truefalse","correct":15,"total":15,"stars":3,"xp":305,"accuracy":100,"duration":84},{"ts":1772727435432,"game":"wordspy","correct":8,"total":8,"stars":3,"xp":89,"accuracy":100,"duration":54},{"ts":1772727539080,"game":"lightning","correct":10,"total":10,"stars":3,"xp":120,"accuracy":100,"duration":58},{"ts":1772727658900,"game":"bubble","correct":8,"total":10,"stars":3,"xp":290,"accuracy":80,"duration":89},{"ts":1772727840509,"game":"truefalse","correct":14,"total":15,"stars":3,"xp":246,"accuracy":93,"duration":52},{"ts":1772727956321,"game":"bubble","correct":8,"total":10,"stars":3,"xp":260,"accuracy":80,"duration":78},{"ts":1772727970426,"game":"bubble","correct":2,"total":2,"stars":1,"xp":50,"accuracy":100,"duration":10},{"ts":1772728949662,"game":"bubble","correct":9,"total":10,"stars":3,"xp":330,"accuracy":90,"duration":44},{"ts":1772729033280,"game":"lightning","correct":10,"total":10,"stars":3,"xp":120,"accuracy":100,"duration":39},{"ts":1772729213622,"game":"bubble","correct":8,"total":10,"stars":3,"xp":260,"accuracy":80,"duration":51},{"ts":1772729235156,"game":"bubble","correct":2,"total":2,"stars":1,"xp":50,"accuracy":100,"duration":17},{"ts":1772729563468,"game":"bubble","correct":7,"total":10,"stars":2,"xp":190,"accuracy":70,"duration":85},{"ts":1772729603049,"game":"bubble","correct":2,"total":3,"stars":1,"xp":60,"accuracy":67,"duration":31},{"ts":1772729615825,"game":"bubble","correct":1,"total":1,"stars":1,"xp":30,"accuracy":100,"duration":6},{"ts":1772785235253,"game":"bubble","correct":8,"total":10,"stars":3,"xp":240,"accuracy":80,"duration":77},{"ts":1772785253657,"game":"bubble","correct":2,"total":2,"stars":1,"xp":50,"accuracy":100,"duration":11},{"ts":1772890794708,"game":"lightning","correct":7,"total":10,"stars":2,"xp":70,"accuracy":70,"duration":66},{"ts":1772890828233,"game":"lightning","correct":2,"total":3,"stars":1,"xp":20,"accuracy":67,"duration":29},{"ts":1772890833892,"game":"lightning","correct":1,"total":1,"stars":1,"xp":10,"accuracy":100,"duration":3},{"ts":1772891049797,"game":"lightning","correct":6,"total":10,"stars":1,"xp":60,"accuracy":60,"duration":205},{"ts":1772891076209,"game":"lightning","correct":3,"total":4,"stars":1,"xp":30,"accuracy":75,"duration":22},{"ts":1772891081808,"game":"lightning","correct":1,"total":1,"stars":1,"xp":10,"accuracy":100,"duration":4},{"ts":1772891237841,"game":"lightning","correct":8,"total":10,"stars":2,"xp":80,"accuracy":80,"duration":61},{"ts":1772891254378,"game":"lightning","correct":2,"total":2,"stars":1,"xp":20,"accuracy":100,"duration":11},{"ts":1772971198203,"game":"truefalse","correct":15,"total":15,"stars":3,"xp":305,"accuracy":100,"duration":72},{"ts":1772979731650,"game":"matchup","correct":15,"total":15,"stars":2,"xp":300,"accuracy":100,"duration":160},{"ts":1772979848939,"game":"lightning","correct":12,"total":15,"stars":3,"xp":120,"accuracy":80,"duration":104}],"words":[{"id":0,"english":"wrong","hebrew":"לא נכון"},{"id":1,"english":"you're","hebrew":"אתה / את (קיצור של you are)"},{"id":2,"english":"welcome","hebrew":"ברוך הבא / בבקשה"},{"id":3,"english":"around","hebrew":"מסביב"},{"id":4,"english":"artist","hebrew":"אמן"},{"id":5,"english":"bridge","hebrew":"גשר"},{"id":6,"english":"castle","hebrew":"טירה"},{"id":7,"english":"celebration","hebrew":"חגיגה"},{"id":8,"english":"clothes","hebrew":"בגדים"},{"id":9,"english":"cousin","hebrew":"בן דוד / בת דודה"},{"id":10,"english":"cupboard","hebrew":"ארון מטבח"},{"id":11,"english":"desert","hebrew":"מדבר"},{"id":12,"english":"detective","hebrew":"בלש"},{"id":13,"english":"dining room","hebrew":"חדר אוכל"},{"id":14,"english":"fire","hebrew":"אש"},{"id":15,"english":"flag","hebrew":"דגל"},{"id":16,"english":"forest","hebrew":"יער"},{"id":17,"english":"mat","hebrew":"שטיחון"},{"id":18,"english":"mirror","hebrew":"מראה"},{"id":19,"english":"outside","hebrew":"בחוץ"},{"id":20,"english":"paint","hebrew":"לצבוע"},{"id":21,"english":"pull","hebrew":"למשוך"},{"id":22,"english":"refrigerator","hebrew":"מקרר"},{"id":23,"english":"rice","hebrew":"אורז"},{"id":24,"english":"river","hebrew":"נהר"},{"id":25,"english":"roof","hebrew":"גג"},{"id":26,"english":"servant","hebrew":"משרת"},{"id":27,"english":"ship","hebrew":"אונייה"},{"id":28,"english":"shower","hebrew":"מקלחת"},{"id":29,"english":"sink","hebrew":"כיור"},{"id":30,"english":"spoon","hebrew":"כף"},{"id":31,"english":"stove","hebrew":"כיריים / תנור"},{"id":32,"english":"straw","hebrew":"קש"},{"id":33,"english":"tent","hebrew":"אוהל"},{"id":34,"english":"thief","hebrew":"גנב"},{"id":35,"english":"throw","hebrew":"לזרוק"},{"id":36,"english":"toilet","hebrew":"שירותים"},{"id":37,"english":"travel","hebrew":"לטייל / לנסוע"},{"id":38,"english":"trip","hebrew":"טיול"},{"id":39,"english":"visit","hebrew":"לבקר"},{"id":40,"english":"weekend","hebrew":"סוף שבוע"},{"id":41,"english":"about","hebrew":"על"},{"id":42,"english":"after","hebrew":"אחרי"},{"id":43,"english":"afternoon","hebrew":"אחר הצהריים"},{"id":44,"english":"all","hebrew":"הכול"},{"id":45,"english":"another","hebrew":"אחר"},{"id":46,"english":"before","hebrew":"לפני"},{"id":47,"english":"breakfast","hebrew":"ארוחת בוקר"},{"id":48,"english":"call","hebrew":"להתקשר / קריאה"},{"id":49,"english":"catch","hebrew":"לתפוס"},{"id":50,"english":"clean","hebrew":"לנקות"},{"id":51,"english":"each","hebrew":"כל אחד"},{"id":52,"english":"evening","hebrew":"ערב"},{"id":53,"english":"everyone","hebrew":"כולם"},{"id":54,"english":"fall","hebrew":"ליפול"},{"id":55,"english":"get","hebrew":"לקבל / להשיג"},{"id":56,"english":"glass","hebrew":"כוס"},{"id":57,"english":"guess","hebrew":"לנחש"},{"id":58,"english":"home","hebrew":"בית"},{"id":59,"english":"kind of","hebrew":"סוג של"},{"id":60,"english":"late","hebrew":"מאוחר"},{"id":61,"english":"look at","hebrew":"להסתכל על"},{"id":62,"english":"lunch","hebrew":"ארוחת צהריים"},{"id":63,"english":"many","hebrew":"הרבה"},{"id":64,"english":"moon","hebrew":"ירח"},{"id":65,"english":"parents","hebrew":"הורים"},{"id":66,"english":"pick up","hebrew":"לאסוף"},{"id":67,"english":"quiet","hebrew":"שקט"},{"id":68,"english":"rich","hebrew":"עשיר"},{"id":69,"english":"sometimes","hebrew":"לפעמים"},{"id":70,"english":"sport","hebrew":"ספורט"},{"id":71,"english":"supper","hebrew":"ארוחת ערב"},{"id":72,"english":"thanks","hebrew":"תודה"},{"id":73,"english":"thing","hebrew":"דבר"},{"id":74,"english":"think","hebrew":"לחשוב"},{"id":75,"english":"too","hebrew":"גם"},{"id":76,"english":"town","hebrew":"עיר / עיירה"},{"id":77,"english":"until","hebrew":"עד"},{"id":78,"english":"us","hebrew":"אותנו"},{"id":79,"english":"work","hebrew":"עבודה"},{"id":80,"english":"world","hebrew":"עולם"},{"id":81,"english":"wood","hebrew":"עץ / עץ (חומר)"},{"id":82,"english":"you're welcome","hebrew":"בבקשה (בתשובה לתודה)"}],"mastery":{"0":{"timesCorrect":14,"timesWrong":4,"masteryLevel":4,"gameModesCorrect":["truefalse","sprint","wordspy","lightning","bingo","mapping"],"lastSeen":1772979201161,"srsInterval":4,"srsNextReview":1773324801161,"recentAnswers":[true,true,true,true,true,true],"justMastered":false,"masteredSince":1772979429068},"1":{"timesCorrect":15,"timesWrong":0,"masteryLevel":4,"gameModesCorrect":["lightning","truefalse","bingo","bubble","mapping"],"lastSeen":1772979024978,"srsInterval":30,"srsNextReview":1775571024978,"recentAnswers":[true,true,true,true,true,true],"justMastered":true,"masteredSince":1772979429068},"2":{"timesCorrect":6,"timesWrong":0,"masteryLevel":2,"gameModesCorrect":["memory","truefalse","mapping"],"lastSeen":1772979236368,"srsInterval":4,"srsNextReview":1773324836368,"recentAnswers":[true,true,true,true,true,true],"justMastered":false,"masteredSince":1772979429068},"3":{"timesCorrect":36,"timesWrong":11,"masteryLevel":5,"gameModesCorrect":["lightning","truefalse","sprint","wordspy","bingo","bubble","matchup","memory","test","mapping"],"lastSeen":1772979167883,"srsInterval":2,"srsNextReview":1773151967883,"recentAnswers":[true,true,true,true,true,true,false,true],"justMastered":false},"4":{"timesCorrect":21,"timesWrong":3,"masteryLevel":5,"gameModesCorrect":["lightning","truefalse","bingo","bubble","matchup","test","mapping"],"lastSeen":1772979793769,"srsInterval":30,"srsNextReview":1775571793769,"recentAnswers":[true,true,true,true,true,true,true,true,true,true],"justMastered":false,"masteredSince":1772979633502,"masteredCorrectCount":2},"5":{"timesCorrect":17,"timesWrong":3,"masteryLevel":4,"gameModesCorrect":["lightning","matchup","truefalse","memory","bubble","test","mapping"],"lastSeen":1772979045346,"srsInterval":30,"srsNextReview":1775571045346,"recentAnswers":[true,true,true,true,true,true,true,true],"justMastered":false,"masteredSince":1772971112002},"6":{"timesCorrect":44,"timesWrong":14,"masteryLevel":5,"gameModesCorrect":["lightning","matchup","sprint","truefalse","bubble","test","bingo","mapping"],"lastSeen":1772979672076,"srsInterval":30,"srsNextReview":1775571672076,"recentAnswers":[true,true,true,true,true,true,true,true,true,true],"justMastered":true,"masteredSince":1772979672076,"masteredCorrectCount":1},"7":{"timesCorrect":11,"timesWrong":0,"masteryLevel":3,"gameModesCorrect":["bubble","lightning","matchup","truefalse","test","mapping"],"lastSeen":1772979765774,"srsInterval":30,"srsNextReview":1775571765774,"recentAnswers":[true,true,true,true,true,true,true,true,true],"justMastered":false,"masteredSince":1772971112002,"masteredCorrectCount":1},"8":{"timesCorrect":21,"timesWrong":5,"masteryLevel":5,"gameModesCorrect":["bubble","matchup","truefalse","test","bingo","lightning","mapping"],"lastSeen":1772979348837,"srsInterval":30,"srsNextReview":1775571348837,"recentAnswers":[true,false,true,true,true,true,true,true],"justMastered":false,"masteredSince":1772971112002},"9":{"timesCorrect":43,"timesWrong":15,"masteryLevel":5,"gameModesCorrect":["bubble","lightning","truefalse","sprint","wordspy","matchup","bingo","mapping"],"lastSeen":1772979731049,"srsInterval":4,"srsNextReview":1773325331049,"recentAnswers":[true,true,false,true,true,true,true,true,true,true],"justMastered":true,"masteredSince":1772979731049,"masteredCorrectCount":1},"10":{"timesCorrect":29,"timesWrong":9,"masteryLevel":5,"gameModesCorrect":["lightning","wordspy","truefalse","bubble","matchup","test","bingo","mapping"],"lastSeen":1772979403212,"srsInterval":30,"srsNextReview":1775571403212,"recentAnswers":[true,true,true,true,true,true,true,true],"justMastered":false,"masteredSince":1772971112002},"11":{"timesCorrect":35,"timesWrong":8,"masteryLevel":5,"gameModesCorrect":["lightning","sprint","truefalse","wordspy","bubble","matchup","test","bingo","mapping"],"lastSeen":1772979773464,"srsInterval":16,"srsNextReview":1774362173464,"recentAnswers":[true,true,true,true,false,false,true,true,true,true],"justMastered":false},"12":{"timesCorrect":19,"timesWrong":4,"masteryLevel":5,"gameModesCorrect":["truefalse","lightning","matchup","sprint","bubble","test","bingo","mapping"],"lastSeen":1772979359163,"srsInterval":30,"srsNextReview":1775571359163,"recentAnswers":[true,true,true,true,true,true,true,true],"justMastered":false,"masteredSince":1772971112002},"13":{"timesCorrect":30,"timesWrong":1,"masteryLevel":5,"gameModesCorrect":["truefalse","lightning","matchup","wordspy","bingo","bubble","test","mapping"],"lastSeen":1772979619089,"srsInterval":30,"srsNextReview":1775571619089,"recentAnswers":[true,true,true,true,true,true,true,true,true,true],"justMastered":true,"masteredSince":1772979619090,"masteredCorrectCount":1},"14":{"timesCorrect":17,"timesWrong":2,"masteryLevel":4,"gameModesCorrect":["bubble","truefalse","sprint","matchup","test","lightning","mapping"],"lastSeen":1772979115704,"srsInterval":30,"srsNextReview":1775571115704,"recentAnswers":[true,true,true,true,true,true,true,true],"justMastered":false,"masteredSince":1772971112002},"15":{"timesCorrect":24,"timesWrong":4,"masteryLevel":5,"gameModesCorrect":["bubble","truefalse","matchup","test","bingo","lightning","mapping"],"lastSeen":1772979714168,"srsInterval":30,"srsNextReview":1775571714168,"recentAnswers":[true,true,true,true,true,true,true,true,true,true],"justMastered":false,"masteredSince":1772971112002,"masteredCorrectCount":1},"16":{"timesCorrect":23,"timesWrong":1,"masteryLevel":5,"gameModesCorrect":["truefalse","sprint","lightning","bubble","matchup","test","mapping"],"lastSeen":1772979710543,"srsInterval":30,"srsNextReview":1775571710543,"recentAnswers":[true,true,true,true,true,true,true,true,true,true],"justMastered":false,"masteredSince":1772971112002,"masteredCorrectCount":1},"17":{"timesCorrect":24,"timesWrong":0,"masteryLevel":5,"gameModesCorrect":["truefalse","bingo","matchup","wordspy","lightning","bubble","test","mapping"],"lastSeen":1772979404993,"srsInterval":30,"srsNextReview":1775571404993,"recentAnswers":[true,true,true,true,true,true,true,true],"justMastered":false,"masteredSince":1772971112002},"18":{"timesCorrect":12,"timesWrong":1,"masteryLevel":3,"gameModesCorrect":["memory","lightning","matchup","bubble","truefalse","test","mapping"],"lastSeen":1772979180890,"srsInterval":30,"srsNextReview":1775571180890,"recentAnswers":[true,true,true,true,true,true,true,true],"justMastered":false,"masteredSince":1772971112002},"19":{"timesCorrect":15,"timesWrong":5,"masteryLevel":4,"gameModesCorrect":["truefalse","bingo","lightning","bubble","matchup","mapping"],"lastSeen":1772979224524,"srsInterval":30,"srsNextReview":1775571224524,"recentAnswers":[true,false,true,true,true,true,true,true],"justMastered":false,"masteredSince":1772971112002},"20":{"timesCorrect":13,"timesWrong":4,"masteryLevel":3,"gameModesCorrect":["truefalse","sprint","lightning","bubble","bingo","matchup","mapping"],"lastSeen":1772979197212,"srsInterval":2,"srsNextReview":1773151997212,"recentAnswers":[true,true,true,true,true,true,false,true],"justMastered":false},"21":{"timesCorrect":13,"timesWrong":3,"masteryLevel":3,"gameModesCorrect":["truefalse","lightning","matchup","wordspy","bubble","test","mapping"],"lastSeen":1772979287405,"srsInterval":30,"srsNextReview":1775571287405,"recentAnswers":[true,true,true,true,true,true],"justMastered":false,"masteredSince":1772971112002},"22":{"timesCorrect":13,"timesWrong":0,"masteryLevel":3,"gameModesCorrect":["truefalse","lightning","matchup","wordspy","bingo","mapping"],"lastSeen":1772979131092,"srsInterval":4,"srsNextReview":1773324731092,"recentAnswers":[true,true,true,true,true,true],"justMastered":false,"masteredSince":1772979429068},"23":{"timesCorrect":21,"timesWrong":4,"masteryLevel":5,"gameModesCorrect":["truefalse","lightning","matchup","bubble","mapping"],"lastSeen":1772979608700,"srsInterval":30,"srsNextReview":1775571608700,"recentAnswers":[true,true,true,true,true,true,true,true,true,true],"justMastered":false,"masteredSince":1772971112002,"masteredCorrectCount":1},"24":{"timesCorrect":12,"timesWrong":1,"masteryLevel":3,"gameModesCorrect":["truefalse","bingo","lightning","bubble","mapping"],"lastSeen":1772979259853,"srsInterval":16,"srsNextReview":1774361659853,"recentAnswers":[true,true,true,true,true,true],"justMastered":false,"masteredSince":1772979429068},"25":{"timesCorrect":6,"timesWrong":0,"masteryLevel":2,"gameModesCorrect":["bubble","truefalse","mapping"],"lastSeen":1772979027468,"srsInterval":8,"srsNextReview":1773670227468,"recentAnswers":[true,true,true,true,true,true],"justMastered":false,"masteredSince":1772979429068},"26":{"timesCorrect":6,"timesWrong":1,"masteryLevel":2,"gameModesCorrect":["bubble","truefalse","mapping"],"lastSeen":1772979175951,"srsInterval":4,"srsNextReview":1773324775951,"recentAnswers":[true,true,true,true,true,true],"justMastered":false,"masteredSince":1772979429068},"27":{"timesCorrect":12,"timesWrong":1,"masteryLevel":3,"gameModesCorrect":["lightning","truefalse","bubble","test","mapping","matchup"],"lastSeen":1772979719682,"srsInterval":4,"srsNextReview":1773325319682,"recentAnswers":[true,true,false,true,true,true,true,true,true,true],"justMastered":true,"masteredSince":1772979719682,"masteredCorrectCount":1},"28":{"timesCorrect":6,"timesWrong":0,"masteryLevel":2,"gameModesCorrect":["bubble","truefalse","mapping"],"lastSeen":1772979133803,"srsInterval":8,"srsNextReview":1773670333803,"recentAnswers":[true,true,true,true,true,true],"justMastered":false,"masteredSince":1772979429068},"29":{"timesCorrect":6,"timesWrong":0,"masteryLevel":2,"gameModesCorrect":["lightning","truefalse","mapping"],"lastSeen":1772979232291,"srsInterval":4,"srsNextReview":1773324590569,"recentAnswers":[true,true,true,true,true,true],"justMastered":false,"masteredSince":1772978995305},"30":{"timesCorrect":2,"timesWrong":2,"masteryLevel":1,"gameModesCorrect":["lightning","truefalse"],"lastSeen":1772979801012,"srsInterval":1,"srsNextReview":1773066201012,"recentAnswers":[false,true,true,false],"justMastered":false},"31":{"timesCorrect":6,"timesWrong":2,"masteryLevel":2,"gameModesCorrect":["lightning","truefalse","bubble","mapping"],"lastSeen":1772979810389,"srsInterval":1,"srsNextReview":1773066210389,"recentAnswers":[true,true,true,true,true,true,false],"justMastered":false,"masteredSince":null,"masteredCorrectCount":0},"32":{"timesCorrect":6,"timesWrong":1,"masteryLevel":2,"gameModesCorrect":["bubble","mapping"],"lastSeen":1772979049989,"srsInterval":4,"srsNextReview":1773324649989,"recentAnswers":[true,true,true,true,true,true],"justMastered":false,"masteredSince":1772979429068},"33":{"timesCorrect":6,"timesWrong":3,"masteryLevel":2,"gameModesCorrect":["bubble","truefalse","mapping"],"lastSeen":1772979193765,"srsInterval":2,"srsNextReview":1773151993765,"recentAnswers":[true,true,true,true,true,true],"justMastered":false,"masteredSince":1772979429068},"34":{"timesCorrect":4,"timesWrong":5,"masteryLevel":1,"gameModesCorrect":["bubble","lightning","truefalse"],"lastSeen":1772979750807,"srsInterval":2,"srsNextReview":1773152550807,"recentAnswers":[true,false,false,false,false,true,true,false,true],"justMastered":false},"35":{"timesCorrect":6,"timesWrong":1,"masteryLevel":2,"gameModesCorrect":["bubble","truefalse","mapping"],"lastSeen":1772979329474,"srsInterval":16,"srsNextReview":1774361729474,"recentAnswers":[true,true,true,true,true,true],"justMastered":false,"masteredSince":1772979429068},"36":{"timesCorrect":6,"timesWrong":0,"masteryLevel":2,"gameModesCorrect":["matchup","truefalse","mapping"],"lastSeen":1772979361752,"srsInterval":4,"srsNextReview":1773324961752,"recentAnswers":[true,true,true,true,true,true],"justMastered":false,"masteredSince":1772979429068},"37":{"timesCorrect":8,"timesWrong":3,"masteryLevel":2,"gameModesCorrect":["truefalse","bubble","test","lightning","mapping"],"lastSeen":1772979845201,"srsInterval":8,"srsNextReview":1773671045201,"recentAnswers":[true,true,true,true,true,false,false,true,true,true],"justMastered":false},"38":{"timesCorrect":6,"timesWrong":2,"masteryLevel":2,"gameModesCorrect":["bubble","mapping"],"lastSeen":1772979023068,"srsInterval":2,"srsNextReview":1773151823068,"recentAnswers":[true,true,true,true,true,true],"justMastered":false,"masteredSince":1772979429068},"39":{"timesCorrect":2,"timesWrong":0,"masteryLevel":1,"gameModesCorrect":["lightning"],"lastSeen":1772979755131,"srsInterval":4,"srsNextReview":1773325355131,"recentAnswers":[true,true],"justMastered":false},"40":{"timesCorrect":9,"timesWrong":4,"masteryLevel":3,"gameModesCorrect":["lightning","bubble","matchup","test","mapping"],"lastSeen":1772979093933,"srsInterval":30,"srsNextReview":1775571093933,"recentAnswers":[true,true,true,true,true,true,true,true],"justMastered":false,"masteredSince":1772971112002},"41":{"timesCorrect":32,"timesWrong":8,"masteryLevel":5,"gameModesCorrect":["sprint","wordspy","matchup","truefalse","bubble","bingo","lightning","test"],"lastSeen":1772979399757,"srsInterval":30,"srsNextReview":1775321251425,"recentAnswers":[true,true,true,true,true,true,true,true],"justMastered":false,"masteredSince":1772971112002},"42":{"timesCorrect":25,"timesWrong":6,"masteryLevel":5,"gameModesCorrect":["lightning","bingo","truefalse","bubble","matchup","memory","test","mapping"],"lastSeen":1772979204145,"srsInterval":30,"srsNextReview":1775571204145,"recentAnswers":[true,true,true,true,true,true,true,true],"justMastered":false,"masteredSince":1772971112002},"43":{"timesCorrect":16,"timesWrong":2,"masteryLevel":4,"gameModesCorrect":["truefalse","wordspy","lightning","bingo","matchup","memory","bubble","test","mapping"],"lastSeen":1772979136684,"srsInterval":30,"srsNextReview":1775571136684,"recentAnswers":[true,false,true,true,true,true,true,true],"justMastered":false,"masteredSince":1772971112002},"44":{"timesCorrect":14,"timesWrong":3,"masteryLevel":4,"gameModesCorrect":["bingo","truefalse","sprint","bubble","matchup","test","lightning"],"lastSeen":1772979014205,"srsInterval":30,"srsNextReview":1775483216821,"recentAnswers":[true,true,true,true,true,true,true,true],"justMastered":false,"masteredSince":1772971112002},"45":{"timesCorrect":21,"timesWrong":4,"masteryLevel":5,"gameModesCorrect":["bingo","truefalse","sprint","bubble","matchup","test","lightning"],"lastSeen":1772979291478,"srsInterval":30,"srsNextReview":1775482769504,"recentAnswers":[true,true,true,true,true,true,true,true],"justMastered":false,"masteredSince":1772971112002},"46":{"timesCorrect":30,"timesWrong":0,"masteryLevel":5,"gameModesCorrect":["lightning","bubble","matchup","truefalse","test","bingo","mapping"],"lastSeen":1772979652739,"srsInterval":30,"srsNextReview":1775571652739,"recentAnswers":[true,true,true,true,true,true,true,true,true,true],"justMastered":false,"masteredSince":1772971112002,"masteredCorrectCount":1},"47":{"timesCorrect":20,"timesWrong":3,"masteryLevel":5,"gameModesCorrect":["lightning","bingo","bubble","memory","matchup","test","truefalse","mapping"],"lastSeen":1772979113603,"srsInterval":30,"srsNextReview":1775571113603,"recentAnswers":[true,true,true,true,true,true,true,true],"justMastered":false,"masteredSince":1772971112002},"48":{"timesCorrect":14,"timesWrong":0,"masteryLevel":4,"gameModesCorrect":["wordspy","lightning","matchup","bubble","test","truefalse","mapping"],"lastSeen":1772979594797,"srsInterval":30,"srsNextReview":1775571594797,"recentAnswers":[true,true,true,true,true,true,true,true,true,true],"justMastered":false,"masteredSince":1772971112002,"masteredCorrectCount":1},"49":{"timesCorrect":15,"timesWrong":2,"masteryLevel":4,"gameModesCorrect":["bubble","scramble","truefalse","sprint","wordspy","matchup","test","mapping","lightning"],"lastSeen":1772979761652,"srsInterval":30,"srsNextReview":1775571761652,"recentAnswers":[true,true,false,true,true,true,true,true,true],"justMastered":true,"masteredSince":1772979761652,"masteredCorrectCount":1},"50":{"timesCorrect":28,"timesWrong":3,"masteryLevel":5,"gameModesCorrect":["memory","lightning","bingo","truefalse","wordspy","matchup","bubble","test","mapping"],"lastSeen":1772979647520,"srsInterval":30,"srsNextReview":1775571647520,"recentAnswers":[true,true,true,true,true,true,true,true,true,true],"justMastered":false,"masteredSince":1772971112002,"masteredCorrectCount":1},"51":{"timesCorrect":22,"timesWrong":2,"masteryLevel":5,"gameModesCorrect":["memory","bingo","truefalse","lightning","bubble","matchup","test","mapping"],"lastSeen":1772979659638,"srsInterval":30,"srsNextReview":1775571659638,"recentAnswers":[true,true,true,true,true,true,true,true,true,true],"justMastered":false,"masteredSince":1772971112002,"masteredCorrectCount":1},"52":{"timesCorrect":10,"timesWrong":1,"masteryLevel":3,"gameModesCorrect":["sprint","truefalse","lightning","bubble","matchup","test","mapping"],"lastSeen":1772979239509,"srsInterval":30,"srsNextReview":1775571239509,"recentAnswers":[true,true,true,true,true,true,true],"justMastered":false,"masteredSince":1772971112002},"53":{"timesCorrect":10,"timesWrong":1,"masteryLevel":3,"gameModesCorrect":["lightning","bingo","bubble","matchup","truefalse","test","mapping"],"lastSeen":1772979343052,"srsInterval":30,"srsNextReview":1775571343052,"recentAnswers":[true,true,true,true,true,true,true,true],"justMastered":false,"masteredSince":1772971112002},"54":{"timesCorrect":10,"timesWrong":1,"masteryLevel":3,"gameModesCorrect":["bingo","truefalse","lightning","bubble","matchup","test","mapping"],"lastSeen":1772979161965,"srsInterval":30,"srsNextReview":1775571161965,"recentAnswers":[true,true,true,true,true,true,true],"justMastered":false,"masteredSince":1772971112002},"55":{"timesCorrect":16,"timesWrong":3,"masteryLevel":4,"gameModesCorrect":["sprint","matchup","truefalse","bubble","test","bingo","mapping"],"lastSeen":1772979032907,"srsInterval":30,"srsNextReview":1775571032907,"recentAnswers":[false,true,true,true,true,true,true,true],"justMastered":false,"masteredSince":1772971112002},"56":{"timesCorrect":13,"timesWrong":1,"masteryLevel":3,"gameModesCorrect":["bubble","matchup","truefalse","test","bingo","wordspy","mapping","lightning"],"lastSeen":1772979790540,"srsInterval":30,"srsNextReview":1775571790540,"recentAnswers":[true,true,true,false,true,true,true,true,true],"justMastered":false},"57":{"timesCorrect":22,"timesWrong":5,"masteryLevel":5,"gameModesCorrect":["bingo","truefalse","lightning","sprint","bubble","matchup","test","mapping"],"lastSeen":1772979141576,"srsInterval":30,"srsNextReview":1775571141576,"recentAnswers":[true,true,true,true,true,true,true,true],"justMastered":false,"masteredSince":1772971112002},"58":{"timesCorrect":15,"timesWrong":0,"masteryLevel":4,"gameModesCorrect":["sprint","truefalse","bubble","matchup","test","lightning","mapping"],"lastSeen":1772979637655,"srsInterval":30,"srsNextReview":1775571637655,"recentAnswers":[true,true,true,true,true,true,true,true,true,true],"justMastered":false,"masteredSince":1772971112002,"masteredCorrectCount":1},"59":{"timesCorrect":20,"timesWrong":0,"masteryLevel":5,"gameModesCorrect":["bingo","lightning","truefalse","wordspy","bubble","matchup","test","mapping"],"lastSeen":1772979848137,"srsInterval":30,"srsNextReview":1775571848137,"recentAnswers":[true,true,true,true,true,true,true,true,true],"justMastered":false,"masteredSince":1772971112002,"masteredCorrectCount":1},"60":{"timesCorrect":16,"timesWrong":0,"masteryLevel":4,"gameModesCorrect":["memory","truefalse","wordspy","bubble","matchup","test","mapping"],"lastSeen":1772979153452,"srsInterval":30,"srsNextReview":1775571153452,"recentAnswers":[true,true,true,true,true,true,true,true],"justMastered":false,"masteredSince":1772971112002},"61":{"timesCorrect":30,"timesWrong":1,"masteryLevel":5,"gameModesCorrect":["bubble","lightning","bingo","matchup","test","truefalse","mapping"],"lastSeen":1772979681725,"srsInterval":30,"srsNextReview":1775571681725,"recentAnswers":[true,true,true,true,true,true,true,true,true,true],"justMastered":false,"masteredSince":1772979588567,"masteredCorrectCount":2},"62":{"timesCorrect":7,"timesWrong":0,"masteryLevel":2,"gameModesCorrect":["wordspy","bubble","truefalse","test","mapping"],"lastSeen":1772979251871,"srsInterval":30,"srsNextReview":1775571251871,"recentAnswers":[true,true,true,true,true,true,true],"justMastered":false,"masteredSince":1772971112002},"63":{"timesCorrect":10,"timesWrong":0,"masteryLevel":3,"gameModesCorrect":["wordspy","bubble","matchup","truefalse","test","mapping"],"lastSeen":1772979351920,"srsInterval":30,"srsNextReview":1775571351920,"recentAnswers":[true,true,true,true,true,true,true,true],"justMastered":false,"masteredSince":1772971112002},"64":{"timesCorrect":15,"timesWrong":0,"masteryLevel":4,"gameModesCorrect":["bubble","bingo","truefalse","matchup","test","wordspy","mapping","lightning"],"lastSeen":1772979757952,"srsInterval":30,"srsNextReview":1775571757952,"recentAnswers":[true,true,true,true,true,true,true,true,true],"justMastered":false,"masteredSince":1772971112002,"masteredCorrectCount":1},"65":{"timesCorrect":10,"timesWrong":2,"masteryLevel":3,"gameModesCorrect":["lightning","bingo","truefalse","wordspy","bubble","test","mapping"],"lastSeen":1772979355720,"srsInterval":30,"srsNextReview":1775571355720,"recentAnswers":[true,true,true,true,true,true],"justMastered":false,"masteredSince":1772979429068},"66":{"timesCorrect":6,"timesWrong":0,"masteryLevel":2,"gameModesCorrect":["catsort","truefalse","test","bubble","mapping"],"lastSeen":1772979221001,"srsInterval":16,"srsNextReview":1774361621001,"recentAnswers":[true,true,true,true,true,true],"justMastered":false,"masteredSince":1772979429068},"67":{"timesCorrect":6,"timesWrong":0,"masteryLevel":2,"gameModesCorrect":["truefalse","wordspy","bubble","mapping"],"lastSeen":1772979374856,"srsInterval":2,"srsNextReview":1773152174856,"recentAnswers":[true,true,true,true,true,true],"justMastered":false,"masteredSince":1772979429068},"68":{"timesCorrect":7,"timesWrong":1,"masteryLevel":2,"gameModesCorrect":["bubble","truefalse","lightning","mapping"],"lastSeen":1772979320860,"srsInterval":16,"srsNextReview":1774361720860,"recentAnswers":[true,true,true,true,true,true],"justMastered":false,"masteredSince":1772979429068},"69":{"timesCorrect":6,"timesWrong":0,"masteryLevel":2,"gameModesCorrect":["bubble","memory","wordspy","mapping"],"lastSeen":1772979089952,"srsInterval":2,"srsNextReview":1773151889952,"recentAnswers":[true,true,true,true,true,true],"masteredSince":1772979429068},"70":{"timesCorrect":6,"timesWrong":0,"masteryLevel":2,"gameModesCorrect":["lightning","mapping"],"lastSeen":1772979303490,"srsInterval":2,"srsNextReview":1773152103490,"recentAnswers":[true,true,true,true,true,true],"justMastered":false,"masteredSince":1772979429068},"71":{"timesCorrect":6,"timesWrong":2,"masteryLevel":2,"gameModesCorrect":["lightning","sprint","mapping"],"lastSeen":1772979036872,"srsInterval":2,"srsNextReview":1773151836872,"recentAnswers":[true,true,true,true,true,true],"justMastered":false,"masteredSince":1772979429068},"72":{"timesCorrect":6,"timesWrong":1,"masteryLevel":2,"gameModesCorrect":["lightning","mapping"],"lastSeen":1772979254577,"srsInterval":2,"srsNextReview":1773152054577,"recentAnswers":[true,true,true,true,true,true],"justMastered":false,"masteredSince":1772979429068},"73":{"timesCorrect":6,"timesWrong":5,"masteryLevel":2,"gameModesCorrect":["sprint","truefalse","wordspy","bubble","mapping"],"lastSeen":1772979783221,"srsInterval":1,"srsNextReview":1773066183221,"recentAnswers":[true,true,true,true,true,true,false,false],"justMastered":false,"masteredSince":null,"masteredCorrectCount":0},"74":{"timesCorrect":6,"timesWrong":0,"masteryLevel":2,"gameModesCorrect":["lightning","mapping"],"lastSeen":1772979068258,"srsInterval":2,"srsNextReview":1773151868258,"recentAnswers":[true,true,true,true,true,true],"justMastered":false,"masteredSince":1772979429068},"75":{"timesCorrect":6,"timesWrong":0,"masteryLevel":2,"gameModesCorrect":["truefalse","bubble","lightning","mapping"],"lastSeen":1772979177894,"srsInterval":8,"srsNextReview":1773670377894,"recentAnswers":[true,true,true,true,true,true],"justMastered":false,"masteredSince":1772979429068},"76":{"timesCorrect":6,"timesWrong":1,"masteryLevel":2,"gameModesCorrect":["bingo","truefalse","lightning","mapping"],"lastSeen":1772979108893,"srsInterval":2,"srsNextReview":1773151908893,"recentAnswers":[true,true,true,true,true,true],"justMastered":false,"masteredSince":1772979429068},"77":{"timesCorrect":7,"timesWrong":3,"masteryLevel":2,"gameModesCorrect":["lightning","bingo","truefalse","sprint"],"lastSeen":1772979824736,"srsInterval":4,"srsNextReview":1773325424736,"recentAnswers":[true,true],"justMastered":false},"78":{"timesCorrect":6,"timesWrong":1,"masteryLevel":2,"gameModesCorrect":["bubble","bingo","truefalse","lightning","mapping"],"lastSeen":1772979262633,"srsInterval":2,"srsNextReview":1773152062633,"recentAnswers":[true,true,true,true,true,true],"justMastered":false,"masteredSince":1772979429068},"79":{"timesCorrect":6,"timesWrong":1,"masteryLevel":2,"gameModesCorrect":["wordspy","truefalse","bubble","matchup","mapping"],"lastSeen":1772979339275,"srsInterval":30,"srsNextReview":1775571339275,"recentAnswers":[true,true,true,true,true,true],"justMastered":false,"masteredSince":1772979429068},"80":{"timesCorrect":6,"timesWrong":2,"masteryLevel":2,"gameModesCorrect":["bubble","mapping"],"lastSeen":1772979249117,"srsInterval":2,"srsNextReview":1773152049117,"recentAnswers":[true,true,true,true,true,true],"justMastered":false,"masteredSince":1772979429068},"81":{"timesCorrect":6,"timesWrong":0,"masteryLevel":2,"gameModesCorrect":["truefalse","mapping"],"lastSeen":1772979283106,"srsInterval":2,"srsNextReview":1773152083106,"recentAnswers":[true,true,true,true,true,true],"masteredSince":1772979429068},"82":{"timesCorrect":7,"timesWrong":0,"masteryLevel":2,"gameModesCorrect":["matchup","mapping","lightning"],"lastSeen":1772979827719,"srsInterval":4,"srsNextReview":1773325427719,"recentAnswers":[true,true,true,true,true,true,true],"justMastered":false,"masteredSince":1772979429068,"masteredCorrectCount":1}},"selection":[],"archive":[],"drip":{"queue":[],"active":[],"batchSize":5},"wordData":[{"english":"wrong","hebrew":"לא נכון","correct":14,"wrong":4,"accuracy":78,"strengthLabel":"mastered","strengthScore":100,"confidenceLevel":"mastered","pctToMastery":100,"streak":6,"modesCount":6,"gameModesCorrect":["truefalse","sprint","wordspy","lightning","bingo","mapping"],"lastSeen":1772979201161,"daysSince":0},{"english":"you're","hebrew":"אתה / את (קיצור של you are)","correct":15,"wrong":0,"accuracy":100,"strengthLabel":"mastered","strengthScore":100,"confidenceLevel":"mastered","pctToMastery":100,"streak":6,"modesCount":5,"gameModesCorrect":["lightning","truefalse","bingo","bubble","mapping"],"lastSeen":1772979024978,"daysSince":0},{"english":"welcome","hebrew":"ברוך הבא / בבקשה","correct":6,"wrong":0,"accuracy":100,"strengthLabel":"mastered","strengthScore":100,"confidenceLevel":"mastered","pctToMastery":100,"streak":6,"modesCount":3,"gameModesCorrect":["memory","truefalse","mapping"],"lastSeen":1772979236368,"daysSince":0},{"english":"around","hebrew":"מסביב","correct":36,"wrong":11,"accuracy":77,"strengthLabel":"good","strengthScore":83,"confidenceLevel":"almost","pctToMastery":83,"streak":5,"modesCount":10,"gameModesCorrect":["lightning","truefalse","sprint","wordspy","bingo","bubble","matchup","memory","test","mapping"],"lastSeen":1772979167883,"daysSince":0},{"english":"artist","hebrew":"אמן","correct":21,"wrong":3,"accuracy":88,"strengthLabel":"mastered","strengthScore":100,"confidenceLevel":"mastered","pctToMastery":100,"streak":6,"modesCount":7,"gameModesCorrect":["lightning","truefalse","bingo","bubble","matchup","test","mapping"],"lastSeen":1772979793769,"daysSince":0},{"english":"bridge","hebrew":"גשר","correct":17,"wrong":3,"accuracy":85,"strengthLabel":"mastered","strengthScore":100,"confidenceLevel":"mastered","pctToMastery":100,"streak":6,"modesCount":7,"gameModesCorrect":["lightning","matchup","truefalse","memory","bubble","test","mapping"],"lastSeen":1772979045346,"daysSince":0},{"english":"castle","hebrew":"טירה","correct":44,"wrong":14,"accuracy":76,"strengthLabel":"mastered","strengthScore":100,"confidenceLevel":"mastered","pctToMastery":100,"streak":6,"modesCount":8,"gameModesCorrect":["lightning","matchup","sprint","truefalse","bubble","test","bingo","mapping"],"lastSeen":1772979672076,"daysSince":0},{"english":"celebration","hebrew":"חגיגה","correct":11,"wrong":0,"accuracy":100,"strengthLabel":"mastered","strengthScore":100,"confidenceLevel":"mastered","pctToMastery":100,"streak":6,"modesCount":6,"gameModesCorrect":["bubble","lightning","matchup","truefalse","test","mapping"],"lastSeen":1772979765774,"daysSince":0},{"english":"clothes","hebrew":"בגדים","correct":21,"wrong":5,"accuracy":81,"strengthLabel":"mastered","strengthScore":100,"confidenceLevel":"mastered","pctToMastery":100,"streak":6,"modesCount":7,"gameModesCorrect":["bubble","matchup","truefalse","test","bingo","lightning","mapping"],"lastSeen":1772979348837,"daysSince":0},{"english":"cousin","hebrew":"בן דוד / בת דודה","correct":43,"wrong":15,"accuracy":74,"strengthLabel":"mastered","strengthScore":100,"confidenceLevel":"mastered","pctToMastery":100,"streak":6,"modesCount":8,"gameModesCorrect":["bubble","lightning","truefalse","sprint","wordspy","matchup","bingo","mapping"],"lastSeen":1772979731049,"daysSince":0},{"english":"cupboard","hebrew":"ארון מטבח","correct":29,"wrong":9,"accuracy":76,"strengthLabel":"mastered","strengthScore":100,"confidenceLevel":"mastered","pctToMastery":100,"streak":6,"modesCount":8,"gameModesCorrect":["lightning","wordspy","truefalse","bubble","matchup","test","bingo","mapping"],"lastSeen":1772979403212,"daysSince":0},{"english":"desert","hebrew":"מדבר","correct":35,"wrong":8,"accuracy":81,"strengthLabel":"learning","strengthScore":67,"confidenceLevel":"learning","pctToMastery":67,"streak":4,"modesCount":9,"gameModesCorrect":["lightning","sprint","truefalse","wordspy","bubble","matchup","test","bingo","mapping"],"lastSeen":1772979773464,"daysSince":0},{"english":"detective","hebrew":"בלש","correct":19,"wrong":4,"accuracy":83,"strengthLabel":"mastered","strengthScore":100,"confidenceLevel":"mastered","pctToMastery":100,"streak":6,"modesCount":8,"gameModesCorrect":["truefalse","lightning","matchup","sprint","bubble","test","bingo","mapping"],"lastSeen":1772979359163,"daysSince":0},{"english":"dining room","hebrew":"חדר אוכל","correct":30,"wrong":1,"accuracy":97,"strengthLabel":"mastered","strengthScore":100,"confidenceLevel":"mastered","pctToMastery":100,"streak":6,"modesCount":8,"gameModesCorrect":["truefalse","lightning","matchup","wordspy","bingo","bubble","test","mapping"],"lastSeen":1772979619089,"daysSince":0},{"english":"fire","hebrew":"אש","correct":17,"wrong":2,"accuracy":89,"strengthLabel":"mastered","strengthScore":100,"confidenceLevel":"mastered","pctToMastery":100,"streak":6,"modesCount":7,"gameModesCorrect":["bubble","truefalse","sprint","matchup","test","lightning","mapping"],"lastSeen":1772979115704,"daysSince":0},{"english":"flag","hebrew":"דגל","correct":24,"wrong":4,"accuracy":86,"strengthLabel":"mastered","strengthScore":100,"confidenceLevel":"mastered","pctToMastery":100,"streak":6,"modesCount":7,"gameModesCorrect":["bubble","truefalse","matchup","test","bingo","lightning","mapping"],"lastSeen":1772979714168,"daysSince":0},{"english":"forest","hebrew":"יער","correct":23,"wrong":1,"accuracy":96,"strengthLabel":"mastered","strengthScore":100,"confidenceLevel":"mastered","pctToMastery":100,"streak":6,"modesCount":7,"gameModesCorrect":["truefalse","sprint","lightning","bubble","matchup","test","mapping"],"lastSeen":1772979710543,"daysSince":0},{"english":"mat","hebrew":"שטיחון","correct":24,"wrong":0,"accuracy":100,"strengthLabel":"mastered","strengthScore":100,"confidenceLevel":"mastered","pctToMastery":100,"streak":6,"modesCount":8,"gameModesCorrect":["truefalse","bingo","matchup","wordspy","lightning","bubble","test","mapping"],"lastSeen":1772979404993,"daysSince":0},{"english":"mirror","hebrew":"מראה","correct":12,"wrong":1,"accuracy":92,"strengthLabel":"mastered","strengthScore":100,"confidenceLevel":"mastered","pctToMastery":100,"streak":6,"modesCount":7,"gameModesCorrect":["memory","lightning","matchup","bubble","truefalse","test","mapping"],"lastSeen":1772979180890,"daysSince":0},{"english":"outside","hebrew":"בחוץ","correct":15,"wrong":5,"accuracy":75,"strengthLabel":"mastered","strengthScore":100,"confidenceLevel":"mastered","pctToMastery":100,"streak":6,"modesCount":6,"gameModesCorrect":["truefalse","bingo","lightning","bubble","matchup","mapping"],"lastSeen":1772979224524,"daysSince":0},{"english":"paint","hebrew":"לצבוע","correct":13,"wrong":4,"accuracy":76,"strengthLabel":"good","strengthScore":83,"confidenceLevel":"almost","pctToMastery":83,"streak":5,"modesCount":7,"gameModesCorrect":["truefalse","sprint","lightning","bubble","bingo","matchup","mapping"],"lastSeen":1772979197212,"daysSince":0},{"english":"pull","hebrew":"למשוך","correct":13,"wrong":3,"accuracy":81,"strengthLabel":"mastered","strengthScore":100,"confidenceLevel":"mastered","pctToMastery":100,"streak":6,"modesCount":7,"gameModesCorrect":["truefalse","lightning","matchup","wordspy","bubble","test","mapping"],"lastSeen":1772979287405,"daysSince":0},{"english":"refrigerator","hebrew":"מקרר","correct":13,"wrong":0,"accuracy":100,"strengthLabel":"mastered","strengthScore":100,"confidenceLevel":"mastered","pctToMastery":100,"streak":6,"modesCount":6,"gameModesCorrect":["truefalse","lightning","matchup","wordspy","bingo","mapping"],"lastSeen":1772979131092,"daysSince":0},{"english":"rice","hebrew":"אורז","correct":21,"wrong":4,"accuracy":84,"strengthLabel":"mastered","strengthScore":100,"confidenceLevel":"mastered","pctToMastery":100,"streak":6,"modesCount":5,"gameModesCorrect":["truefalse","lightning","matchup","bubble","mapping"],"lastSeen":1772979608700,"daysSince":0},{"english":"river","hebrew":"נהר","correct":12,"wrong":1,"accuracy":92,"strengthLabel":"mastered","strengthScore":100,"confidenceLevel":"mastered","pctToMastery":100,"streak":6,"modesCount":5,"gameModesCorrect":["truefalse","bingo","lightning","bubble","mapping"],"lastSeen":1772979259853,"daysSince":0},{"english":"roof","hebrew":"גג","correct":6,"wrong":0,"accuracy":100,"strengthLabel":"mastered","strengthScore":100,"confidenceLevel":"mastered","pctToMastery":100,"streak":6,"modesCount":3,"gameModesCorrect":["bubble","truefalse","mapping"],"lastSeen":1772979027468,"daysSince":0},{"english":"servant","hebrew":"משרת","correct":6,"wrong":1,"accuracy":86,"strengthLabel":"mastered","strengthScore":100,"confidenceLevel":"mastered","pctToMastery":100,"streak":6,"modesCount":3,"gameModesCorrect":["bubble","truefalse","mapping"],"lastSeen":1772979175951,"daysSince":0},{"english":"ship","hebrew":"אונייה","correct":12,"wrong":1,"accuracy":92,"strengthLabel":"mastered","strengthScore":100,"confidenceLevel":"mastered","pctToMastery":100,"streak":6,"modesCount":6,"gameModesCorrect":["lightning","truefalse","bubble","test","mapping","matchup"],"lastSeen":1772979719682,"daysSince":0},{"english":"shower","hebrew":"מקלחת","correct":6,"wrong":0,"accuracy":100,"strengthLabel":"mastered","strengthScore":100,"confidenceLevel":"mastered","pctToMastery":100,"streak":6,"modesCount":3,"gameModesCorrect":["bubble","truefalse","mapping"],"lastSeen":1772979133803,"daysSince":0},{"english":"sink","hebrew":"כיור","correct":6,"wrong":0,"accuracy":100,"strengthLabel":"mastered","strengthScore":100,"confidenceLevel":"mastered","pctToMastery":100,"streak":6,"modesCount":3,"gameModesCorrect":["lightning","truefalse","mapping"],"lastSeen":1772979232291,"daysSince":0},{"english":"spoon","hebrew":"כף","correct":2,"wrong":2,"accuracy":50,"strengthLabel":"struggling","strengthScore":33,"confidenceLevel":"struggling","pctToMastery":33,"streak":2,"modesCount":2,"gameModesCorrect":["lightning","truefalse"],"lastSeen":1772979801012,"daysSince":0},{"english":"stove","hebrew":"כיריים / תנור","correct":6,"wrong":2,"accuracy":75,"strengthLabel":"good","strengthScore":83,"confidenceLevel":"almost","pctToMastery":83,"streak":5,"modesCount":4,"gameModesCorrect":["lightning","truefalse","bubble","mapping"],"lastSeen":1772979810389,"daysSince":0},{"english":"straw","hebrew":"קש","correct":6,"wrong":1,"accuracy":86,"strengthLabel":"mastered","strengthScore":100,"confidenceLevel":"mastered","pctToMastery":100,"streak":6,"modesCount":2,"gameModesCorrect":["bubble","mapping"],"lastSeen":1772979049989,"daysSince":0},{"english":"tent","hebrew":"אוהל","correct":6,"wrong":3,"accuracy":67,"strengthLabel":"mastered","strengthScore":100,"confidenceLevel":"mastered","pctToMastery":100,"streak":6,"modesCount":3,"gameModesCorrect":["bubble","truefalse","mapping"],"lastSeen":1772979193765,"daysSince":0},{"english":"thief","hebrew":"גנב","correct":4,"wrong":5,"accuracy":44,"strengthLabel":"learning","strengthScore":50,"confidenceLevel":"learning","pctToMastery":50,"streak":3,"modesCount":3,"gameModesCorrect":["bubble","lightning","truefalse"],"lastSeen":1772979750807,"daysSince":0},{"english":"throw","hebrew":"לזרוק","correct":6,"wrong":1,"accuracy":86,"strengthLabel":"mastered","strengthScore":100,"confidenceLevel":"mastered","pctToMastery":100,"streak":6,"modesCount":3,"gameModesCorrect":["bubble","truefalse","mapping"],"lastSeen":1772979329474,"daysSince":0},{"english":"toilet","hebrew":"שירותים","correct":6,"wrong":0,"accuracy":100,"strengthLabel":"mastered","strengthScore":100,"confidenceLevel":"mastered","pctToMastery":100,"streak":6,"modesCount":3,"gameModesCorrect":["matchup","truefalse","mapping"],"lastSeen":1772979361752,"daysSince":0},{"english":"travel","hebrew":"לטייל / לנסוע","correct":8,"wrong":3,"accuracy":73,"strengthLabel":"learning","strengthScore":67,"confidenceLevel":"learning","pctToMastery":67,"streak":4,"modesCount":5,"gameModesCorrect":["truefalse","bubble","test","lightning","mapping"],"lastSeen":1772979845201,"daysSince":0},{"english":"trip","hebrew":"טיול","correct":6,"wrong":2,"accuracy":75,"strengthLabel":"mastered","strengthScore":100,"confidenceLevel":"mastered","pctToMastery":100,"streak":6,"modesCount":2,"gameModesCorrect":["bubble","mapping"],"lastSeen":1772979023068,"daysSince":0},{"english":"visit","hebrew":"לבקר","correct":2,"wrong":0,"accuracy":100,"strengthLabel":"struggling","strengthScore":33,"confidenceLevel":"struggling","pctToMastery":33,"streak":2,"modesCount":1,"gameModesCorrect":["lightning"],"lastSeen":1772979755131,"daysSince":0},{"english":"weekend","hebrew":"סוף שבוע","correct":9,"wrong":4,"accuracy":69,"strengthLabel":"mastered","strengthScore":100,"confidenceLevel":"mastered","pctToMastery":100,"streak":6,"modesCount":5,"gameModesCorrect":["lightning","bubble","matchup","test","mapping"],"lastSeen":1772979093933,"daysSince":0},{"english":"about","hebrew":"על","correct":32,"wrong":8,"accuracy":80,"strengthLabel":"mastered","strengthScore":100,"confidenceLevel":"mastered","pctToMastery":100,"streak":6,"modesCount":8,"gameModesCorrect":["sprint","wordspy","matchup","truefalse","bubble","bingo","lightning","test"],"lastSeen":1772979399757,"daysSince":0},{"english":"after","hebrew":"אחרי","correct":25,"wrong":6,"accuracy":81,"strengthLabel":"mastered","strengthScore":100,"confidenceLevel":"mastered","pctToMastery":100,"streak":6,"modesCount":8,"gameModesCorrect":["lightning","bingo","truefalse","bubble","matchup","memory","test","mapping"],"lastSeen":1772979204145,"daysSince":0},{"english":"afternoon","hebrew":"אחר הצהריים","correct":16,"wrong":2,"accuracy":89,"strengthLabel":"mastered","strengthScore":100,"confidenceLevel":"mastered","pctToMastery":100,"streak":6,"modesCount":9,"gameModesCorrect":["truefalse","wordspy","lightning","bingo","matchup","memory","bubble","test","mapping"],"lastSeen":1772979136684,"daysSince":0},{"english":"all","hebrew":"הכול","correct":14,"wrong":3,"accuracy":82,"strengthLabel":"mastered","strengthScore":100,"confidenceLevel":"mastered","pctToMastery":100,"streak":6,"modesCount":7,"gameModesCorrect":["bingo","truefalse","sprint","bubble","matchup","test","lightning"],"lastSeen":1772979014205,"daysSince":0},{"english":"another","hebrew":"אחר","correct":21,"wrong":4,"accuracy":84,"strengthLabel":"mastered","strengthScore":100,"confidenceLevel":"mastered","pctToMastery":100,"streak":6,"modesCount":7,"gameModesCorrect":["bingo","truefalse","sprint","bubble","matchup","test","lightning"],"lastSeen":1772979291478,"daysSince":0},{"english":"before","hebrew":"לפני","correct":30,"wrong":0,"accuracy":100,"strengthLabel":"mastered","strengthScore":100,"confidenceLevel":"mastered","pctToMastery":100,"streak":6,"modesCount":7,"gameModesCorrect":["lightning","bubble","matchup","truefalse","test","bingo","mapping"],"lastSeen":1772979652739,"daysSince":0},{"english":"breakfast","hebrew":"ארוחת בוקר","correct":20,"wrong":3,"accuracy":87,"strengthLabel":"mastered","strengthScore":100,"confidenceLevel":"mastered","pctToMastery":100,"streak":6,"modesCount":8,"gameModesCorrect":["lightning","bingo","bubble","memory","matchup","test","truefalse","mapping"],"lastSeen":1772979113603,"daysSince":0},{"english":"call","hebrew":"להתקשר / קריאה","correct":14,"wrong":0,"accuracy":100,"strengthLabel":"mastered","strengthScore":100,"confidenceLevel":"mastered","pctToMastery":100,"streak":6,"modesCount":7,"gameModesCorrect":["wordspy","lightning","matchup","bubble","test","truefalse","mapping"],"lastSeen":1772979594797,"daysSince":0},{"english":"catch","hebrew":"לתפוס","correct":15,"wrong":2,"accuracy":88,"strengthLabel":"mastered","strengthScore":100,"confidenceLevel":"mastered","pctToMastery":100,"streak":6,"modesCount":9,"gameModesCorrect":["bubble","scramble","truefalse","sprint","wordspy","matchup","test","mapping","lightning"],"lastSeen":1772979761652,"daysSince":0},{"english":"clean","hebrew":"לנקות","correct":28,"wrong":3,"accuracy":90,"strengthLabel":"mastered","strengthScore":100,"confidenceLevel":"mastered","pctToMastery":100,"streak":6,"modesCount":9,"gameModesCorrect":["memory","lightning","bingo","truefalse","wordspy","matchup","bubble","test","mapping"],"lastSeen":1772979647520,"daysSince":0},{"english":"each","hebrew":"כל אחד","correct":22,"wrong":2,"accuracy":92,"strengthLabel":"mastered","strengthScore":100,"confidenceLevel":"mastered","pctToMastery":100,"streak":6,"modesCount":8,"gameModesCorrect":["memory","bingo","truefalse","lightning","bubble","matchup","test","mapping"],"lastSeen":1772979659638,"daysSince":0},{"english":"evening","hebrew":"ערב","correct":10,"wrong":1,"accuracy":91,"strengthLabel":"mastered","strengthScore":100,"confidenceLevel":"mastered","pctToMastery":100,"streak":6,"modesCount":7,"gameModesCorrect":["sprint","truefalse","lightning","bubble","matchup","test","mapping"],"lastSeen":1772979239509,"daysSince":0},{"english":"everyone","hebrew":"כולם","correct":10,"wrong":1,"accuracy":91,"strengthLabel":"mastered","strengthScore":100,"confidenceLevel":"mastered","pctToMastery":100,"streak":6,"modesCount":7,"gameModesCorrect":["lightning","bingo","bubble","matchup","truefalse","test","mapping"],"lastSeen":1772979343052,"daysSince":0},{"english":"fall","hebrew":"ליפול","correct":10,"wrong":1,"accuracy":91,"strengthLabel":"mastered","strengthScore":100,"confidenceLevel":"mastered","pctToMastery":100,"streak":6,"modesCount":7,"gameModesCorrect":["bingo","truefalse","lightning","bubble","matchup","test","mapping"],"lastSeen":1772979161965,"daysSince":0},{"english":"get","hebrew":"לקבל / להשיג","correct":16,"wrong":3,"accuracy":84,"strengthLabel":"mastered","strengthScore":100,"confidenceLevel":"mastered","pctToMastery":100,"streak":6,"modesCount":7,"gameModesCorrect":["sprint","matchup","truefalse","bubble","test","bingo","mapping"],"lastSeen":1772979032907,"daysSince":0},{"english":"glass","hebrew":"כוס","correct":13,"wrong":1,"accuracy":93,"strengthLabel":"good","strengthScore":83,"confidenceLevel":"almost","pctToMastery":83,"streak":5,"modesCount":8,"gameModesCorrect":["bubble","matchup","truefalse","test","bingo","wordspy","mapping","lightning"],"lastSeen":1772979790540,"daysSince":0},{"english":"guess","hebrew":"לנחש","correct":22,"wrong":5,"accuracy":81,"strengthLabel":"mastered","strengthScore":100,"confidenceLevel":"mastered","pctToMastery":100,"streak":6,"modesCount":8,"gameModesCorrect":["bingo","truefalse","lightning","sprint","bubble","matchup","test","mapping"],"lastSeen":1772979141576,"daysSince":0},{"english":"home","hebrew":"בית","correct":15,"wrong":0,"accuracy":100,"strengthLabel":"mastered","strengthScore":100,"confidenceLevel":"mastered","pctToMastery":100,"streak":6,"modesCount":7,"gameModesCorrect":["sprint","truefalse","bubble","matchup","test","lightning","mapping"],"lastSeen":1772979637655,"daysSince":0},{"english":"kind of","hebrew":"סוג של","correct":20,"wrong":0,"accuracy":100,"strengthLabel":"mastered","strengthScore":100,"confidenceLevel":"mastered","pctToMastery":100,"streak":6,"modesCount":8,"gameModesCorrect":["bingo","lightning","truefalse","wordspy","bubble","matchup","test","mapping"],"lastSeen":1772979848137,"daysSince":0},{"english":"late","hebrew":"מאוחר","correct":16,"wrong":0,"accuracy":100,"strengthLabel":"mastered","strengthScore":100,"confidenceLevel":"mastered","pctToMastery":100,"streak":6,"modesCount":7,"gameModesCorrect":["memory","truefalse","wordspy","bubble","matchup","test","mapping"],"lastSeen":1772979153452,"daysSince":0},{"english":"look at","hebrew":"להסתכל על","correct":30,"wrong":1,"accuracy":97,"strengthLabel":"mastered","strengthScore":100,"confidenceLevel":"mastered","pctToMastery":100,"streak":6,"modesCount":7,"gameModesCorrect":["bubble","lightning","bingo","matchup","test","truefalse","mapping"],"lastSeen":1772979681725,"daysSince":0},{"english":"lunch","hebrew":"ארוחת צהריים","correct":7,"wrong":0,"accuracy":100,"strengthLabel":"mastered","strengthScore":100,"confidenceLevel":"mastered","pctToMastery":100,"streak":6,"modesCount":5,"gameModesCorrect":["wordspy","bubble","truefalse","test","mapping"],"lastSeen":1772979251871,"daysSince":0},{"english":"many","hebrew":"הרבה","correct":10,"wrong":0,"accuracy":100,"strengthLabel":"mastered","strengthScore":100,"confidenceLevel":"mastered","pctToMastery":100,"streak":6,"modesCount":6,"gameModesCorrect":["wordspy","bubble","matchup","truefalse","test","mapping"],"lastSeen":1772979351920,"daysSince":0},{"english":"moon","hebrew":"ירח","correct":15,"wrong":0,"accuracy":100,"strengthLabel":"mastered","strengthScore":100,"confidenceLevel":"mastered","pctToMastery":100,"streak":6,"modesCount":8,"gameModesCorrect":["bubble","bingo","truefalse","matchup","test","wordspy","mapping","lightning"],"lastSeen":1772979757952,"daysSince":0},{"english":"parents","hebrew":"הורים","correct":10,"wrong":2,"accuracy":83,"strengthLabel":"mastered","strengthScore":100,"confidenceLevel":"mastered","pctToMastery":100,"streak":6,"modesCount":7,"gameModesCorrect":["lightning","bingo","truefalse","wordspy","bubble","test","mapping"],"lastSeen":1772979355720,"daysSince":0},{"english":"pick up","hebrew":"לאסוף","correct":6,"wrong":0,"accuracy":100,"strengthLabel":"mastered","strengthScore":100,"confidenceLevel":"mastered","pctToMastery":100,"streak":6,"modesCount":5,"gameModesCorrect":["catsort","truefalse","test","bubble","mapping"],"lastSeen":1772979221001,"daysSince":0},{"english":"quiet","hebrew":"שקט","correct":6,"wrong":0,"accuracy":100,"strengthLabel":"mastered","strengthScore":100,"confidenceLevel":"mastered","pctToMastery":100,"streak":6,"modesCount":4,"gameModesCorrect":["truefalse","wordspy","bubble","mapping"],"lastSeen":1772979374856,"daysSince":0},{"english":"rich","hebrew":"עשיר","correct":7,"wrong":1,"accuracy":88,"strengthLabel":"mastered","strengthScore":100,"confidenceLevel":"mastered","pctToMastery":100,"streak":6,"modesCount":4,"gameModesCorrect":["bubble","truefalse","lightning","mapping"],"lastSeen":1772979320860,"daysSince":0},{"english":"sometimes","hebrew":"לפעמים","correct":6,"wrong":0,"accuracy":100,"strengthLabel":"mastered","strengthScore":100,"confidenceLevel":"mastered","pctToMastery":100,"streak":6,"modesCount":4,"gameModesCorrect":["bubble","memory","wordspy","mapping"],"lastSeen":1772979089952,"daysSince":0},{"english":"sport","hebrew":"ספורט","correct":6,"wrong":0,"accuracy":100,"strengthLabel":"mastered","strengthScore":100,"confidenceLevel":"mastered","pctToMastery":100,"streak":6,"modesCount":2,"gameModesCorrect":["lightning","mapping"],"lastSeen":1772979303490,"daysSince":0},{"english":"supper","hebrew":"ארוחת ערב","correct":6,"wrong":2,"accuracy":75,"strengthLabel":"mastered","strengthScore":100,"confidenceLevel":"mastered","pctToMastery":100,"streak":6,"modesCount":3,"gameModesCorrect":["lightning","sprint","mapping"],"lastSeen":1772979036872,"daysSince":0},{"english":"thanks","hebrew":"תודה","correct":6,"wrong":1,"accuracy":86,"strengthLabel":"mastered","strengthScore":100,"confidenceLevel":"mastered","pctToMastery":100,"streak":6,"modesCount":2,"gameModesCorrect":["lightning","mapping"],"lastSeen":1772979254577,"daysSince":0},{"english":"thing","hebrew":"דבר","correct":6,"wrong":5,"accuracy":55,"strengthLabel":"learning","strengthScore":67,"confidenceLevel":"learning","pctToMastery":67,"streak":4,"modesCount":5,"gameModesCorrect":["sprint","truefalse","wordspy","bubble","mapping"],"lastSeen":1772979783221,"daysSince":0},{"english":"think","hebrew":"לחשוב","correct":6,"wrong":0,"accuracy":100,"strengthLabel":"mastered","strengthScore":100,"confidenceLevel":"mastered","pctToMastery":100,"streak":6,"modesCount":2,"gameModesCorrect":["lightning","mapping"],"lastSeen":1772979068258,"daysSince":0},{"english":"too","hebrew":"גם","correct":6,"wrong":0,"accuracy":100,"strengthLabel":"mastered","strengthScore":100,"confidenceLevel":"mastered","pctToMastery":100,"streak":6,"modesCount":4,"gameModesCorrect":["truefalse","bubble","lightning","mapping"],"lastSeen":1772979177894,"daysSince":0},{"english":"town","hebrew":"עיר / עיירה","correct":6,"wrong":1,"accuracy":86,"strengthLabel":"mastered","strengthScore":100,"confidenceLevel":"mastered","pctToMastery":100,"streak":6,"modesCount":4,"gameModesCorrect":["bingo","truefalse","lightning","mapping"],"lastSeen":1772979108893,"daysSince":0},{"english":"until","hebrew":"עד","correct":7,"wrong":3,"accuracy":70,"strengthLabel":"struggling","strengthScore":33,"confidenceLevel":"struggling","pctToMastery":33,"streak":2,"modesCount":4,"gameModesCorrect":["lightning","bingo","truefalse","sprint"],"lastSeen":1772979824736,"daysSince":0},{"english":"us","hebrew":"אותנו","correct":6,"wrong":1,"accuracy":86,"strengthLabel":"mastered","strengthScore":100,"confidenceLevel":"mastered","pctToMastery":100,"streak":6,"modesCount":5,"gameModesCorrect":["bubble","bingo","truefalse","lightning","mapping"],"lastSeen":1772979262633,"daysSince":0},{"english":"work","hebrew":"עבודה","correct":6,"wrong":1,"accuracy":86,"strengthLabel":"mastered","strengthScore":100,"confidenceLevel":"mastered","pctToMastery":100,"streak":6,"modesCount":5,"gameModesCorrect":["wordspy","truefalse","bubble","matchup","mapping"],"lastSeen":1772979339275,"daysSince":0},{"english":"world","hebrew":"עולם","correct":6,"wrong":2,"accuracy":75,"strengthLabel":"mastered","strengthScore":100,"confidenceLevel":"mastered","pctToMastery":100,"streak":6,"modesCount":2,"gameModesCorrect":["bubble","mapping"],"lastSeen":1772979249117,"daysSince":0},{"english":"wood","hebrew":"עץ / עץ (חומר)","correct":6,"wrong":0,"accuracy":100,"strengthLabel":"mastered","strengthScore":100,"confidenceLevel":"mastered","pctToMastery":100,"streak":6,"modesCount":2,"gameModesCorrect":["truefalse","mapping"],"lastSeen":1772979283106,"daysSince":0},{"english":"you're welcome","hebrew":"בבקשה (בתשובה לתודה)","correct":7,"wrong":0,"accuracy":100,"strengthLabel":"mastered","strengthScore":100,"confidenceLevel":"mastered","pctToMastery":100,"streak":6,"modesCount":3,"gameModesCorrect":["matchup","mapping","lightning"],"lastSeen":1772979827719,"daysSince":0}],"totalWords":83,"streak":7,"latestTest":{"date":1772717032453,"totalWords":40,"correct":38,"wrong":2,"grade":"A","pct":95,"wrongWords":[{"english":"desert","hebrew":"מדבר"},{"english":"cousin","hebrew":"בן דוד / בת דודה"}]},"lang":"he","dailySnapshot":{"date":"Sun Mar 08 2026","categories":{"wrong":"learning","you're":"good","welcome":"struggling","around":"good","artist":"good","bridge":"mastered","castle":"good","celebration":"mastered","clothes":"mastered","cousin":"good","cupboard":"mastered","desert":"learning","detective":"mastered","dining room":"good","fire":"mastered","flag":"mastered","forest":"mastered","mat":"mastered","mirror":"mastered","outside":"mastered","paint":"good","pull":"mastered","refrigerator":"struggling","rice":"mastered","river":"learning","roof":"learning","servant":"struggling","ship":"good","shower":"learning","sink":"struggling","spoon":"struggling","stove":"learning","straw":"struggling","tent":"struggling","thief":"struggling","throw":"learning","toilet":"struggling","travel":"learning","trip":"struggling","visit":"struggling","weekend":"mastered","about":"mastered","after":"mastered","afternoon":"mastered","all":"mastered","another":"mastered","before":"mastered","breakfast":"mastered","call":"mastered","catch":"good","clean":"mastered","each":"mastered","evening":"mastered","everyone":"mastered","fall":"mastered","get":"mastered","glass":"good","guess":"mastered","home":"mastered","kind of":"mastered","late":"mastered","look at":"good","lunch":"mastered","many":"mastered","moon":"mastered","parents":"good","pick up":"learning","quiet":"struggling","rich":"learning","sometimes":"learning","sport":"struggling","supper":"struggling","thanks":"struggling","thing":"struggling","think":"struggling","too":"learning","town":"struggling","until":"struggling","us":"struggling","work":"good","world":"struggling","wood":"struggling","you're welcome":"struggling"}}}